MANIFEST.in
setup.py
opencc/__init__.py
opencc/version.py
opencc/bin/opencc.dll
opencc/bin/opencc.exe
opencc/bin/opencc_dict.exe
opencc/data/mix2zhs.ini
opencc/data/mix2zht.ini
opencc/data/simp_to_trad_characters.ocd
opencc/data/simp_to_trad_phrases.ocd
opencc/data/trad_to_simp_characters.ocd
opencc/data/trad_to_simp_phrases.ocd
opencc/data/zhs2zht.ini
opencc/data/zht2zhs.ini
opencc_python.egg-info/PKG-INFO
opencc_python.egg-info/SOURCES.txt
opencc_python.egg-info/dependency_links.txt
opencc_python.egg-info/requires.txt
opencc_python.egg-info/top_level.txt