Metadata-Version: 1.0
Name: opencc-python
Version: 0.1
Summary: A Python wrapper for Open Chinese Convert
Home-page: http://bitbucket.org/victorlin/opencc_python
Author: Victor Lin
Author-email: bornstub@gmail.com
License: MIT
Platform: UNKNOWN
